{
  "title": "Salah Steps",
  "steps": [
    {
      "id": "standingForNiyyah",
      "heading": "Standing For Niyyah",
      "content": [
        {
          "eleType": "h5",
          "id": "",
          "classes": "",
          "insertion": {
            "location": "after",
            "recitationId": ["AllahuAkbar"]
          },
          "txt": ["Step 1: Standing"]
        },
        {
          "eleType": "p",
          "id": "",
          "classes": "",
          "insertion": {
            "location": "none",
            "recitationId": [""]
          },
          "txt": [
            "The person turns towards the direction of the Qiblah, (the sacred Mosque at Makkah), intending by heart to perform the Fajr (Dawn) prayer."
          ]
        },
        {
          "eleType": "note",
          "id": "",
          "classes": "is-small smallTxt",
          "insertion": {
            "location": "none",
            "recitationId": [""]
          },
          "txt": [
            "Note:",
            "The person should not pronounce his/her intention openly because neither the Prophet (PBUH) nor his companions used to utter their intention for prayer. Thus, pronouncing the intention in a loud voice is an innovation and is totally rejected."
          ]
        }
      ]
    },
    {
      "id": "takbiir",
      "heading": "Takbiir",
      "content": [
        {
          "eleType": "h5",
          "id": "",
          "classes": "",
          "insertion": {
            "location": "none",
            "recitationId": [""]
          },
          "txt": ["Step 1.2: Takbiir"]
        },
        {
          "eleType": "p",
          "id": "",
          "classes": "",
          "insertion": {
            "location": "after",
            "recitationId": ["AllahuAkbar"]
          },
          "txt": [
            "The person then raises both hands up to the level of the shoulders or near the lobes of the ears, pronounces the 'Takbiiratil Ihraam' by saying 'ALLAHU AKBAR' 'الله أكبر' and places both hands over the chest with the right hand over the left."
          ]
        },
        {
          "eleType": "p",
          "id": "",
          "classes": "",
          "insertion": {
            "location": "none",
            "recitationId": [""]
          },
          "txt": [
            "By reciting the 'Takbiiratil - Ihraam', the person thus, resolves for prayer and enters into a state of worship and is thenceforth required to call to mind the majesty and glory of 'Allah (SWT)' and to dedicate his intentions, recitations and actions to Him alone until the end of the prayer. While praying the person is required to direct his eyes downwards at the spot of prostration."
          ]
        }
      ]
    },
    {
      "id": "openingSupplication",
      "heading": "Opening Supplication - Hamd",
      "content": [
        {
          "eleType": "h5",
          "id": "",
          "classes": "",
          "insertion": {
            "location": "none",
            "recitationId": [""]
          },
          "txt": ["Step 1.3: Opening Supplication"]
        },
        {
          "eleType": "p",
          "id": "",
          "classes": "",
          "insertion": {
            "location": "after",
            "recitationId": ["Hamd1", "Hamd2", "Hamd3"]
          },
          "txt": [
            "The person then recites in a low voice an opening supplication for the prayer. Here below are three of the supplications which the Prophet (PBUH) used to practice and the Muslim is exhorted to memorize at least one of them for recitation each time a prayer is performed:"
          ]
        },
        {
          "eleType": "p",
          "id": "",
          "classes": "",
          "insertion": {
            "location": "after",
            "recitationId": ["AuzoBillah"]
          },
          "txt": [
            "The person then silently invokes "Allah (SWT)" by saying:"
          ]
        }
      ]
    }

  ]
}
